{"rklstudio": [{"id": 201711, "mc": 68, "oc": 3}], "rkopuk": [{"id": 211377, "mc": 335, "oc": 9}], "rk800": [{"id": 219585, "mc": 18, "oc": 0}], "rk": [{"id": 238171, "mc": 116, "oc": 21}, {"id": 251159, "mc": 18, "oc": 1}, {"id": 260665, "mc": 27, "oc": 11}, {"id": 356928, "mc": 7, "oc": 2}, {"id": 397599, "mc": 89, "oc": 14}], "rkano": [{"id": 249154, "mc": 184, "oc": 5}], "rkive": [{"id": 257701, "mc": 3, "oc": 0}], "rkn": [{"id": 258399, "mc": 213, "oc": 53}, {"id": 303691, "mc": 131, "oc": 32}, {"id": 351671, "mc": 53, "oc": 17}, {"id": 394592, "mc": 213, "oc": 28}], "rkjha": [{"id": 264412, "mc": 5, "oc": 1}], "rkstormer": [{"id": 331078, "mc": 13, "oc": 3}], "rk91": [{"id": 334795, "mc": 114, "oc": 4}], "rklauer": [{"id": 339675, "mc": 191, "oc": 41}], "rkuhn": [{"id": 397268, "mc": 64, "oc": 2}]}