{"slimy": [{"id": 201700, "mc": 42, "oc": 11}], "sleep": [{"id": 202633, "mc": 13, "oc": 1}, {"id": 259591, "mc": 104279, "oc": 11216}, {"id": 381048, "mc": 294, "oc": 23}], "slay": [{"id": 207540, "mc": 741, "oc": 104}], "slick": [{"id": 214613, "mc": 1323, "oc": 7}, {"id": 363284, "mc": 41, "oc": 7}], "slapshot": [{"id": 219453, "mc": 53, "oc": 10}], "sla": [{"id": 225326, "mc": 110, "oc": 10}, {"id": 266671, "mc": 11, "oc": 1}], "slurp": [{"id": 229132, "mc": 274, "oc": 47}, {"id": 229132, "mc": 274, "oc": 47}], "slouch": [{"id": 234727, "mc": 49, "oc": 0}], "slip": [{"id": 236655, "mc": 755, "oc": 9}, {"id": 251611, "mc": 2219, "oc": 128}, {"id": 345100, "mc": 7, "oc": 0}, {"id": 399822, "mc": 189, "oc": 14}], "slash": [{"id": 241371, "mc": 30, "oc": 10}, {"id": 248822, "mc": 432, "oc": 14}, {"id": 280132, "mc": 459526, "oc": 14106}, {"id": 346739, "mc": 2, "oc": 0}], "slashin": [{"id": 248230, "mc": 7, "oc": 2}], "sl": [{"id": 256651, "mc": 43, "oc": 9}, {"id": 258949, "mc": 2134, "oc": 85}, {"id": 316977, "mc": 190, "oc": 25}, {"id": 384576, "mc": 28252, "oc": 2958}], "slack": [{"id": 268166, "mc": 1760, "oc": 190}], "slammer": [{"id": 270380, "mc": 4912, "oc": 1302}], "slooty": [{"id": 271436, "mc": 221, "oc": 4}], "slackersecret": [{"id": 281421, "mc": 15, "oc": 6}], "sleeveles": [{"id": 281594, "mc": 128, "oc": 28}], "sled": [{"id": 282162, "mc": 46, "oc": 13}, {"id": 315274, "mc": 30, "oc": 10}], "slp": [{"id": 291417, "mc": 793, "oc": 52}], "sleeples": [{"id": 293074, "mc": 5, "oc": 3}], "slt": [{"id": 299939, "mc": 64, "oc": 10}], "slop": [{"id": 300824, "mc": 94, "oc": 23}], "sloler": [{"id": 303609, "mc": 650, "oc": 191}], "slothest": [{"id": 304659, "mc": 1176, "oc": 12}], "slesar6razriada": [{"id": 306718, "mc": 221, "oc": 4}], "sluttynes": [{"id": 308275, "mc": 62, "oc": 12}], "slave": [{"id": 308512, "mc": 146, "oc": 36}, {"id": 319935, "mc": 38, "oc": 12}, {"id": 320990, "mc": 1, "oc": 0}], "slitherin": [{"id": 314149, "mc": 9478, "oc": 113}], "slogro": [{"id": 318653, "mc": 211, "oc": 10}], "slow": [{"id": 319810, "mc": 1949, "oc": 11}], "slumber": [{"id": 319982, "mc": 110, "oc": 17}], "slime": [{"id": 325671, "mc": 35, "oc": 7}, {"id": 340410, "mc": 41, "oc": 10}, {"id": 355493, "mc": 41, "oc": 4}, {"id": 367374, "mc": 4, "oc": 2}], "slingshot": [{"id": 325713, "mc": 3259, "oc": 184}], "slrr": [{"id": 329091, "mc": 4366, "oc": 330}], "slayer": [{"id": 336693, "mc": 36, "oc": 9}, {"id": 357778, "mc": 80, "oc": 9}], "sleepy": [{"id": 337836, "mc": 35, "oc": 6}], "slept": [{"id": 339850, "mc": 386, "oc": 11}], "slur": [{"id": 346169, "mc": 164, "oc": 33}], "slightly": [{"id": 347604, "mc": 121, "oc": 14}], "sludge": [{"id": 355489, "mc": 31, "oc": 12}], "sli": [{"id": 356162, "mc": 19, "oc": 8}], "slusheeworld": [{"id": 360866, "mc": 35, "oc": 3}], "slowpic": [{"id": 363560, "mc": 195, "oc": 31}], "slide": [{"id": 374321, "mc": 398, "oc": 32}], "slk": [{"id": 376893, "mc": 678, "oc": 107}], "slamat": [{"id": 384354, "mc": 71, "oc": 29}], "slauka": [{"id": 384908, "mc": 150, "oc": 52}], "slshverse": [{"id": 386800, "mc": 100, "oc": 10}], "slaverose": [{"id": 393331, "mc": 1, "oc": 0}], "slg": [{"id": 396242, "mc": 12, "oc": 6}], "slugsoc": [{"id": 396755, "mc": 1492, "oc": 255}]}