{"gxn9ejpk2t": [{"id": 200358, "mc": 147, "oc": 35}], "gxrxmpp9mz": [{"id": 201045, "mc": 18277, "oc": 2489}], "gxx9jh": [{"id": 201238, "mc": 171, "oc": 31}], "gx3qteberz": [{"id": 201563, "mc": 5, "oc": 2}], "gxjq4kjxvp": [{"id": 202178, "mc": 307, "oc": 27}], "gxjqpu8": [{"id": 203210, "mc": 4560, "oc": 992}], "gxbdyb9t4e": [{"id": 203243, "mc": 115, "oc": 22}], "gxdnxgtdxh": [{"id": 204258, "mc": 18132, "oc": 1224}], "gxbcyp5sa": [{"id": 204956, "mc": 38, "oc": 7}], "gxxevcwx4m": [{"id": 205185, "mc": 14, "oc": 4}], "gxcuqkf5wa": [{"id": 205414, "mc": 3, "oc": 0}], "gxadkhn": [{"id": 207074, "mc": 1030, "oc": 304}], "gxwq7uxqrz": [{"id": 208118, "mc": 6, "oc": 0}], "gxcf8v54w9": [{"id": 208144, "mc": 20, "oc": 5}], "gxwadxv": [{"id": 208372, "mc": 1, "oc": 0}], "gxv6zaugjp": [{"id": 208510, "mc": 65, "oc": 12}], "gxpatbrpvm": [{"id": 210662, "mc": 220, "oc": 38}], "gxhenda": [{"id": 210859, "mc": 70, "oc": 11}], "gxmkcpg3fd": [{"id": 211319, "mc": 53, "oc": 5}], "gxjcsprcgb": [{"id": 212311, "mc": 1379, "oc": 50}], "gx2tzud": [{"id": 212789, "mc": 1, "oc": 0}], "gxbr4tkcwr": [{"id": 215518, "mc": 1841, "oc": 117}], "gxpcyr4sgq": [{"id": 216059, "mc": 2, "oc": 1}], "gx2bygf4gx": [{"id": 217039, "mc": 194, "oc": 47}], "gxktvhg29b": [{"id": 217530, "mc": 433, "oc": 52}], "gxrqcrrkex": [{"id": 217639, "mc": 307, "oc": 84}], "gxjvth3ddy": [{"id": 219471, "mc": 11, "oc": 2}], "gxd2v38": [{"id": 220234, "mc": 524, "oc": 80}], "gxyfhz2qqk": [{"id": 220485, "mc": 660, "oc": 58}], "gxmbfng": [{"id": 220649, "mc": 45201, "oc": 4071}], "gxgame": [{"id": 221018, "mc": 49359, "oc": 3270}], "gxaunsmgq3": [{"id": 221292, "mc": 1, "oc": 0}], "gx9gve8vyz": [{"id": 221500, "mc": 181239, "oc": 1262}], "gxajyer2fx": [{"id": 222177, "mc": 1511, "oc": 220}], "gxdu4pz": [{"id": 222393, "mc": 3, "oc": 0}], "gxsnvhv": [{"id": 222822, "mc": 13, "oc": 0}], "gxc3eg9pau": [{"id": 223089, "mc": 1151, "oc": 27}], "gx8uzc5": [{"id": 223497, "mc": 813, "oc": 86}], "gxzt5n3wdc": [{"id": 224032, "mc": 9837, "oc": 173}], "gxs8nxm": [{"id": 224068, "mc": 49, "oc": 1}], "gxtym9x": [{"id": 224850, "mc": 28, "oc": 7}], "gxywa8xsxj": [{"id": 224852, "mc": 594, "oc": 121}], "gxrbh2jfc4": [{"id": 224883, "mc": 42, "oc": 13}], "gxhy28k4s2": [{"id": 224895, "mc": 172, "oc": 9}], "gxuskr6htb": [{"id": 224937, "mc": 325, "oc": 41}], "gxm8qmn": [{"id": 225135, "mc": 77, "oc": 23}], "gxbsgwxqrx": [{"id": 225184, "mc": 2, "oc": 0}], "gxvmpzcs8b": [{"id": 225229, "mc": 68, "oc": 28}], "gx2g99dbhz": [{"id": 226851, "mc": 2427, "oc": 29}], "gxa5bfd": [{"id": 226935, "mc": 11, "oc": 6}], "gxhxeg7": [{"id": 227152, "mc": 1, "oc": 0}], "gxsz4d9": [{"id": 227771, "mc": 33, "oc": 4}], "gxhhxgh": [{"id": 227808, "mc": 21, "oc": 3}], "gxtff26": [{"id": 228146, "mc": 36, "oc": 7}], "gxurttg": [{"id": 228452, "mc": 3, "oc": 1}], "gxvvgfrgcb": [{"id": 228574, "mc": 1298, "oc": 198}], "gxtr5d5d5w": [{"id": 229577, "mc": 17580, "oc": 312}], "gxyhjszjpb": [{"id": 229718, "mc": 74, "oc": 7}], "gxzmmdvcqj": [{"id": 230064, "mc": 11, "oc": 2}], "gxqffhxgjf": [{"id": 231131, "mc": 2, "oc": 1}], "gxmyspsvpv": [{"id": 231182, "mc": 6, "oc": 2}], "gxezwrz": [{"id": 231568, "mc": 1, "oc": 0}], "gxt8ghv": [{"id": 232191, "mc": 562, "oc": 96}], "gxd4u9ramd": [{"id": 233086, "mc": 7847, "oc": 99}], "gxhjcwbbwm": [{"id": 233272, "mc": 5, "oc": 1}], "gxku33r": [{"id": 233276, "mc": 47, "oc": 13}], "gxpvbwfth7": [{"id": 233984, "mc": 760, "oc": 9}], "gxmpkdq": [{"id": 234314, "mc": 29, "oc": 6}], "gxwtzu3ttr": [{"id": 234802, "mc": 26, "oc": 7}], "gxhcuwcu7a": [{"id": 235586, "mc": 3114, "oc": 688}], "gxdbbfu": [{"id": 235725, "mc": 45, "oc": 8}], "gxqeq6te7x": [{"id": 236559, "mc": 57, "oc": 14}], "gxttygk3ck": [{"id": 236832, "mc": 854, "oc": 112}], "gxjq88nnxk": [{"id": 237454, "mc": 15, "oc": 5}], "gxn29wdc5j": [{"id": 238081, "mc": 22, "oc": 7}], "gxtevuc": [{"id": 238195, "mc": 103, "oc": 21}], "gxavxry": [{"id": 238514, "mc": 56, "oc": 16}], "gx4wbdw": [{"id": 238971, "mc": 1, "oc": 0}], "gxr47xgys": [{"id": 239169, "mc": 1127, "oc": 134}], "gxbpgazvyy": [{"id": 239368, "mc": 23, "oc": 6}], "gxaw2w6y8": [{"id": 239446, "mc": 54, "oc": 19}], "gxrtsrk": [{"id": 239679, "mc": 4425, "oc": 243}], "gxdprv3": [{"id": 239728, "mc": 167, "oc": 17}], "gxkz5h8vm": [{"id": 239859, "mc": 95, "oc": 19}], "gxj8afw": [{"id": 240380, "mc": 35, "oc": 2}], "gxkfh46wnk": [{"id": 241484, "mc": 1, "oc": 0}], "gxq9gvfdy": [{"id": 241549, "mc": 424, "oc": 20}], "gx8v9fy2hk": [{"id": 241739, "mc": 2622, "oc": 388}], "gxdbmg6": [{"id": 242570, "mc": 53, "oc": 14}], "gxcyqpbgfy": [{"id": 242830, "mc": 147, "oc": 35}], "gx4bqgu": [{"id": 243333, "mc": 2137, "oc": 119}], "gxttpu334h": [{"id": 243386, "mc": 188, "oc": 52}], "gxxjkt5jwt": [{"id": 243563, "mc": 93, "oc": 19}], "gxztpv5jw2": [{"id": 244408, "mc": 1, "oc": 0}], "gxy6xwwjte": [{"id": 244608, "mc": 5, "oc": 3}], "gxgydfa": [{"id": 244615, "mc": 11471, "oc": 1504}], "gxw3pzd": [{"id": 244813, "mc": 81, "oc": 11}], "gxpthffs5u": [{"id": 245076, "mc": 9, "oc": 3}], "gx2mxrr3dp": [{"id": 245114, "mc": 4997, "oc": 30}], "gxtuhb5": [{"id": 245257, "mc": 262, "oc": 68}], "gxmb9zpwz2": [{"id": 245294, "mc": 18, "oc": 3}], "gxbwdrujbh": [{"id": 245759, "mc": 12, "oc": 3}], "gxfdvhet6k": [{"id": 245915, "mc": 7078, "oc": 617}], "gxwvhym": [{"id": 246400, "mc": 410, "oc": 73}], "gxxwwjgxad": [{"id": 246540, "mc": 2200, "oc": 48}], "gxkbxqqyu7": [{"id": 247027, "mc": 142, "oc": 32}], "gx28qqmcgn": [{"id": 247239, "mc": 160, "oc": 40}], "gxbtkxkkdu": [{"id": 248430, "mc": 27, "oc": 8}], "gxq79ru": [{"id": 248746, "mc": 53, "oc": 11}], "gxfhytscee": [{"id": 249087, "mc": 2, "oc": 2}], "gxevy7xfee": [{"id": 249299, "mc": 13895, "oc": 274}], "gxy8jy4": [{"id": 250305, "mc": 364, "oc": 70}], "gxfga3x": [{"id": 250788, "mc": 15, "oc": 4}], "gxxjcmww3j": [{"id": 251521, "mc": 2446, "oc": 14}], "gxuhey5": [{"id": 251973, "mc": 45, "oc": 6}], "gxe4fp9": [{"id": 252733, "mc": 649, "oc": 143}], "gxgddtpcqm": [{"id": 253010, "mc": 4, "oc": 3}], "gxc4cxb": [{"id": 253082, "mc": 34, "oc": 9}], "gxbpaj6": [{"id": 253260, "mc": 29, "oc": 5}], "gx5ykrw": [{"id": 253768, "mc": 16, "oc": 1}], "gxrbfbbmtd": [{"id": 253916, "mc": 7, "oc": 5}], "gx9uahwvt": [{"id": 254494, "mc": 690, "oc": 3}], "gxsvpjwfyu": [{"id": 254747, "mc": 6, "oc": 3}], "gxy9ht4": [{"id": 257036, "mc": 681, "oc": 202}], "gxfsddzjxw": [{"id": 257111, "mc": 512, "oc": 53}], "gxssxbyeaj": [{"id": 258193, "mc": 34, "oc": 11}], "gxhuxhkyg": [{"id": 258522, "mc": 47, "oc": 13}], "gxjesxmm8u": [{"id": 258546, "mc": 24, "oc": 6}], "gxynakvcg7": [{"id": 258651, "mc": 66, "oc": 20}], "gxcauvmmfx": [{"id": 259115, "mc": 1, "oc": 0}], "gxxe2fyewg": [{"id": 259201, "mc": 1559, "oc": 276}], "gxdezwjzgm": [{"id": 260139, "mc": 115, "oc": 22}], "gxxexxtfce": [{"id": 260156, "mc": 1049, "oc": 14}], "gx3uqac": [{"id": 260361, "mc": 204, "oc": 78}], "gxejmjayrh": [{"id": 260942, "mc": 1271, "oc": 53}], "gx8kcvsupe": [{"id": 261291, "mc": 211, "oc": 14}], "gxeznhmswc": [{"id": 261336, "mc": 282, "oc": 15}], "gxzzvgjef": [{"id": 261555, "mc": 11, "oc": 4}], "gxv6hkprbf": [{"id": 261653, "mc": 8, "oc": 5}], "gxrhd9w5px": [{"id": 262497, "mc": 140, "oc": 11}], "gxhxccwu2k": [{"id": 262616, "mc": 2600, "oc": 357}], "gx3nghw": [{"id": 262875, "mc": 51, "oc": 4}], "gxjdpeugsf": [{"id": 262999, "mc": 19, "oc": 10}], "gxq3rdp": [{"id": 263036, "mc": 21, "oc": 5}], "gxrfgdt": [{"id": 263185, "mc": 399, "oc": 51}], "gxzy2heyef": [{"id": 263803, "mc": 1, "oc": 0}], "gxenqp5": [{"id": 264304, "mc": 148, "oc": 33}], "gxdbnzr2ct": [{"id": 264602, "mc": 19, "oc": 6}], "gxhdc6szte": [{"id": 264831, "mc": 253, "oc": 88}], "gx9epss3x": [{"id": 265207, "mc": 1284, "oc": 77}], "gxkwuukc2y": [{"id": 266594, "mc": 133, "oc": 13}], "gxgqwpx": [{"id": 267332, "mc": 380, "oc": 71}], "gxxpvwhz8v": [{"id": 268990, "mc": 11, "oc": 2}], "gxaam2bmta": [{"id": 269718, "mc": 1, "oc": 0}], "gx7rxpnumr": [{"id": 269931, "mc": 7, "oc": 0}], "gxvw2st": [{"id": 270085, "mc": 56, "oc": 21}], "gxysnz": [{"id": 270165, "mc": 5, "oc": 2}], "gxvfxz96gn": [{"id": 271218, "mc": 23, "oc": 0}], "gxeywq7vyh": [{"id": 273113, "mc": 292, "oc": 45}], "gx7tmc5": [{"id": 273465, "mc": 122, "oc": 2}], "gxk72zv": [{"id": 273855, "mc": 52, "oc": 3}], "gx6atpeemz": [{"id": 274198, "mc": 64, "oc": 18}], "gxmfpvzezm": [{"id": 274548, "mc": 10148, "oc": 129}], "gxkg7v": [{"id": 275191, "mc": 2, "oc": 1}], "gxrpmcd": [{"id": 276602, "mc": 63, "oc": 8}], "gxvhh4utv8": [{"id": 276784, "mc": 210, "oc": 11}], "gx6kujjz8y": [{"id": 277082, "mc": 7262, "oc": 971}], "gx4pync": [{"id": 278041, "mc": 449, "oc": 45}], "gxsffgtqma": [{"id": 278503, "mc": 1, "oc": 0}], "gxu8t9kjmt": [{"id": 279818, "mc": 8, "oc": 6}], "gxjxf2n": [{"id": 280221, "mc": 77, "oc": 21}], "gxhdneafja": [{"id": 280270, "mc": 1528, "oc": 257}], "gxqqyyn": [{"id": 280562, "mc": 76, "oc": 29}], "gxnnjga6j6": [{"id": 280783, "mc": 11, "oc": 1}], "gxddtthxzv": [{"id": 280852, "mc": 15681, "oc": 1238}], "gxpg4zsk5r": [{"id": 280923, "mc": 2, "oc": 0}], "gxhy2s4nqf": [{"id": 281165, "mc": 1, "oc": 0}], "gxhn4v4": [{"id": 281195, "mc": 33, "oc": 11}], "gxvtjq78mp": [{"id": 282419, "mc": 5, "oc": 2}], "gxgacukrdf": [{"id": 282765, "mc": 1217, "oc": 222}], "gxhtmrzzww": [{"id": 282887, "mc": 50, "oc": 6}], "gxutqmknqx": [{"id": 283702, "mc": 10, "oc": 1}], "gxmzetnntz": [{"id": 283759, "mc": 8327, "oc": 804}], "gxp2fve5vq": [{"id": 284647, "mc": 5, "oc": 2}], "gxzy2z2": [{"id": 285344, "mc": 1, "oc": 0}], "gxpkvx4cs5": [{"id": 285930, "mc": 589, "oc": 2}], "gx8qyty": [{"id": 286244, "mc": 37, "oc": 12}], "gxbju5n": [{"id": 286509, "mc": 22, "oc": 5}], "gxexwk": [{"id": 287213, "mc": 3543, "oc": 227}], "gxs9kfzd7q": [{"id": 287445, "mc": 7, "oc": 1}], "gxfux9d8g8": [{"id": 287938, "mc": 19, "oc": 7}], "gx5jbwan7": [{"id": 288517, "mc": 45, "oc": 2}], "gxafyrcgg": [{"id": 289584, "mc": 37, "oc": 15}], "gxmeuecqjx": [{"id": 289661, "mc": 37, "oc": 6}], "gxazk5sxtp": [{"id": 290080, "mc": 1198, "oc": 66}], "gxw2xgj7wk": [{"id": 290086, "mc": 489, "oc": 108}], "gxjd8gd": [{"id": 290371, "mc": 4251, "oc": 68}], "gxxj4ae": [{"id": 291007, "mc": 143, "oc": 19}], "gxdqac6p6a": [{"id": 292142, "mc": 14, "oc": 5}], "gxdtjpddg9": [{"id": 292226, "mc": 38, "oc": 6}], "gxnzqfum8v": [{"id": 292231, "mc": 20, "oc": 6}], "gx2zuvvacf": [{"id": 292549, "mc": 62, "oc": 7}], "gxhktppkwm": [{"id": 292691, "mc": 19, "oc": 9}], "gxz5gp92xq": [{"id": 293050, "mc": 42, "oc": 15}], "gxjs2a7dev": [{"id": 293300, "mc": 128, "oc": 7}], "gxgvpzr": [{"id": 293324, "mc": 3, "oc": 1}], "gxxdzr5ugk": [{"id": 294315, "mc": 106, "oc": 31}], "gxe4dwb": [{"id": 294765, "mc": 109, "oc": 22}], "gx8cnz9dba": [{"id": 296634, "mc": 4043, "oc": 109}], "gxmrvagvwe": [{"id": 297005, "mc": 20, "oc": 3}], "gxastdv": [{"id": 297104, "mc": 7, "oc": 4}], "gx9rjmf": [{"id": 297528, "mc": 177, "oc": 57}], "gxzqfta": [{"id": 298515, "mc": 97, "oc": 12}], "gxudmq9x6k": [{"id": 299388, "mc": 8, "oc": 3}], "gxxnz6a": [{"id": 299595, "mc": 56, "oc": 24}], "gxfb8e7": [{"id": 299692, "mc": 24, "oc": 9}], "gxd2ubf": [{"id": 299886, "mc": 26, "oc": 11}], "gxvkq8qwyb": [{"id": 300223, "mc": 257, "oc": 41}], "gxkvypn": [{"id": 300264, "mc": 121, "oc": 19}], "gx87agbbyn": [{"id": 301005, "mc": 148, "oc": 51}], "gx3p9pa": [{"id": 301770, "mc": 1921, "oc": 564}], "gxvbfwqqz3": [{"id": 303189, "mc": 2263, "oc": 9}], "gxzpzjpbf4": [{"id": 303727, "mc": 326, "oc": 35}], "gxtq657gsb": [{"id": 303914, "mc": 5, "oc": 2}], "gx9wny4": [{"id": 304640, "mc": 360, "oc": 44}], "gxhmyuts9w": [{"id": 304899, "mc": 72, "oc": 2}], "gxysdwe": [{"id": 305234, "mc": 292, "oc": 25}], "gxcxnpumbm": [{"id": 305942, "mc": 486, "oc": 48}], "gxftjswwbj": [{"id": 306000, "mc": 93, "oc": 20}], "gxmr6yee23": [{"id": 306080, "mc": 11, "oc": 7}], "gxheetsdad": [{"id": 307334, "mc": 325, "oc": 53}], "gxvdhqfcf": [{"id": 309008, "mc": 53, "oc": 14}], "gxrxqpw3rg": [{"id": 309726, "mc": 25074, "oc": 5061}], "gxbufq5aut": [{"id": 311775, "mc": 6, "oc": 4}], "gxyxaz6hgm": [{"id": 312921, "mc": 124, "oc": 20}], "gxerzzrcnz": [{"id": 313333, "mc": 42, "oc": 7}], "gxcwauunzj": [{"id": 313803, "mc": 27, "oc": 1}], "gxxseejuxk": [{"id": 313838, "mc": 278, "oc": 31}], "gxbhmjdvfe": [{"id": 314095, "mc": 577, "oc": 63}], "gxszm37j3k": [{"id": 314668, "mc": 93, "oc": 19}], "gx4gurm4nt": [{"id": 315366, "mc": 78, "oc": 19}], "gxv6n2y34a": [{"id": 316161, "mc": 35, "oc": 11}], "gxxfmqbcu3": [{"id": 317067, "mc": 934, "oc": 24}], "gxkktnta5p": [{"id": 317503, "mc": 4450, "oc": 377}], "gxxe9bt": [{"id": 317772, "mc": 6, "oc": 0}], "gx4tatzyh7": [{"id": 318257, "mc": 108, "oc": 5}], "gxqvhbbppb": [{"id": 318562, "mc": 1903, "oc": 56}], "gxrtbstawk": [{"id": 319203, "mc": 4, "oc": 0}], "gxjxsqe": [{"id": 320537, "mc": 339, "oc": 79}], "gxqc3sq": [{"id": 320822, "mc": 141, "oc": 34}], "gxzbytywbg": [{"id": 320858, "mc": 24800, "oc": 940}], "gx5tnfqpgb": [{"id": 321236, "mc": 757, "oc": 199}], "gx4vk8tskd": [{"id": 322279, "mc": 2, "oc": 0}], "gxxw9xw7c7": [{"id": 322832, "mc": 2, "oc": 1}], "gxupjaf": [{"id": 323316, "mc": 403, "oc": 33}], "gxbf8gbjjz": [{"id": 323930, "mc": 189, "oc": 44}], "gxuv2k5aa4": [{"id": 324173, "mc": 42, "oc": 17}], "gx485nhn2k": [{"id": 324345, "mc": 93, "oc": 10}], "gxgy5m59sy": [{"id": 325366, "mc": 85, "oc": 20}], "gxzapzvehf": [{"id": 325568, "mc": 196, "oc": 17}], "gxqp8wtar6": [{"id": 326285, "mc": 100, "oc": 5}], "gxwpwdcawg": [{"id": 327136, "mc": 9934, "oc": 10}], "gx8wsjw4s9": [{"id": 327350, "mc": 8, "oc": 2}], "gxmcg2cbzr": [{"id": 327494, "mc": 2, "oc": 0}], "gx7qmap": [{"id": 327987, "mc": 27, "oc": 9}], "gxgcyr9bg2": [{"id": 328080, "mc": 50, "oc": 8}], "gxpvrvxjwf": [{"id": 328503, "mc": 141, "oc": 47}], "gxwha5qqxt": [{"id": 328717, "mc": 371, "oc": 27}], "gxeqrg9epb": [{"id": 328810, "mc": 94, "oc": 4}], "gxxfnpr4yr": [{"id": 329296, "mc": 25, "oc": 4}], "gxegv7nrxt": [{"id": 329667, "mc": 253, "oc": 20}], "gxhde6auje": [{"id": 329680, "mc": 191, "oc": 72}], "gxftqvc": [{"id": 329816, "mc": 535, "oc": 13}], "gxsge6u": [{"id": 329922, "mc": 27, "oc": 3}], "gxqdxzsmkp": [{"id": 330925, "mc": 246, "oc": 46}], "gxfkpd6": [{"id": 331838, "mc": 2, "oc": 0}], "gxw299u": [{"id": 333166, "mc": 45, "oc": 2}], "gxmwxnfvzf": [{"id": 335173, "mc": 559, "oc": 24}], "gxrja83": [{"id": 335676, "mc": 5, "oc": 2}], "gxngfrrmre": [{"id": 335930, "mc": 229, "oc": 95}], "gxkhxvy": [{"id": 335933, "mc": 71, "oc": 4}], "gx8g7twqy": [{"id": 335951, "mc": 26, "oc": 18}], "gxjjthh": [{"id": 336424, "mc": 45166, "oc": 7878}], "gxbr7fkuzp": [{"id": 336479, "mc": 2, "oc": 0}], "gx5pasg": [{"id": 336991, "mc": 821, "oc": 119}], "gx5rw6f": [{"id": 337329, "mc": 34, "oc": 0}], "gxgbaxsp45": [{"id": 338774, "mc": 89, "oc": 6}], "gxfbzhm": [{"id": 339025, "mc": 506, "oc": 80}], "gxnqm6wdum": [{"id": 339138, "mc": 133, "oc": 34}], "gxtdyetbxf": [{"id": 339985, "mc": 24, "oc": 7}], "gxtkgfxcbh": [{"id": 340057, "mc": 12, "oc": 6}], "gxvpuhq": [{"id": 341888, "mc": 26, "oc": 4}], "gxxw7g6": [{"id": 342519, "mc": 1, "oc": 1}], "gxumzyb": [{"id": 342832, "mc": 7, "oc": 1}], "gxkva4garm": [{"id": 343091, "mc": 192, "oc": 65}], "gxbuzfrwnz": [{"id": 343233, "mc": 3, "oc": 2}], "gx9r4pkvtn": [{"id": 344228, "mc": 28, "oc": 7}], "gxzv26v": [{"id": 344409, "mc": 9, "oc": 6}], "gxuta4xvfh": [{"id": 345290, "mc": 38, "oc": 7}], "gxgjd2tfzq": [{"id": 345449, "mc": 28, "oc": 1}], "gxwenwzmst": [{"id": 345545, "mc": 71, "oc": 6}], "gxnxxsnp7q": [{"id": 346148, "mc": 22, "oc": 3}], "gxdjhz45zy": [{"id": 346534, "mc": 40, "oc": 10}], "gxuthnuerq": [{"id": 347161, "mc": 12, "oc": 0}], "gxd4r8h": [{"id": 347607, "mc": 1044, "oc": 22}], "gxama3mqtx": [{"id": 348150, "mc": 215, "oc": 9}], "gxpybkz5gu": [{"id": 349270, "mc": 13, "oc": 6}], "gxx9phmy8": [{"id": 350139, "mc": 22, "oc": 7}], "gxt9jqu3nk": [{"id": 350297, "mc": 97, "oc": 7}], "gxzqwheakp": [{"id": 350748, "mc": 6, "oc": 0}], "gx7rb6a": [{"id": 350908, "mc": 78, "oc": 29}], "gxdgznc": [{"id": 351598, "mc": 257, "oc": 46}], "gxsmqvmmcy": [{"id": 352016, "mc": 1272, "oc": 34}], "gxzj24v96c": [{"id": 352086, "mc": 41, "oc": 21}], "gx45gctav8": [{"id": 353031, "mc": 2566, "oc": 13}], "gx6jpbuseb": [{"id": 353839, "mc": 6, "oc": 1}], "gx3xde5": [{"id": 354554, "mc": 396, "oc": 100}], "gxfshup2nm": [{"id": 355317, "mc": 10, "oc": 0}], "gxnv6bacqa": [{"id": 355731, "mc": 134, "oc": 16}], "gxqg3j95pc": [{"id": 355884, "mc": 9, "oc": 3}], "gx4nxwn": [{"id": 356996, "mc": 21, "oc": 2}], "gxq9kpd": [{"id": 358111, "mc": 5, "oc": 0}], "gx6zwaguuh": [{"id": 358434, "mc": 23, "oc": 4}], "gx7tdtydrj": [{"id": 358718, "mc": 175, "oc": 12}], "gxreuezqta": [{"id": 359892, "mc": 24, "oc": 2}], "gx6qvuyxru": [{"id": 360717, "mc": 2433, "oc": 317}], "gx27hqy": [{"id": 361010, "mc": 24, "oc": 5}], "gxvdjacsxm": [{"id": 361200, "mc": 1498, "oc": 59}], "gxafd5rybd": [{"id": 361473, "mc": 59, "oc": 3}], "gxxkmrm": [{"id": 362528, "mc": 13, "oc": 2}], "gxgndc3kcr": [{"id": 362994, "mc": 30, "oc": 3}], "gxmedmee2p": [{"id": 363811, "mc": 9, "oc": 3}], "gx8qxaujtw": [{"id": 365878, "mc": 25, "oc": 0}], "gxuy5vwpwx": [{"id": 367208, "mc": 97, "oc": 17}], "gxxepxagtn": [{"id": 367513, "mc": 17, "oc": 6}], "gxnd8pyeaw": [{"id": 367876, "mc": 18, "oc": 2}], "gxne5nz": [{"id": 367900, "mc": 165, "oc": 21}], "gxmqwdtfna": [{"id": 367960, "mc": 209, "oc": 6}], "gxaqattcmx": [{"id": 367968, "mc": 11392, "oc": 1192}], "gxtje75": [{"id": 368068, "mc": 2944, "oc": 569}], "gx8whyj7jm": [{"id": 368360, "mc": 129, "oc": 29}], "gxuv5a48un": [{"id": 368773, "mc": 41, "oc": 5}], "gxqkxahbu3": [{"id": 368969, "mc": 45, "oc": 11}], "gxuhrey": [{"id": 368998, "mc": 37, "oc": 6}], "gxzfudzjdd": [{"id": 369036, "mc": 865, "oc": 143}], "gxp663rw2w": [{"id": 369230, "mc": 2, "oc": 1}], "gxrtfeq": [{"id": 370556, "mc": 26, "oc": 1}], "gx3gyd2qt": [{"id": 370568, "mc": 44, "oc": 11}], "gxyfz9a6re": [{"id": 370674, "mc": 55, "oc": 23}], "gxb36curw2": [{"id": 371348, "mc": 48, "oc": 9}], "gxtvexsxrd": [{"id": 371812, "mc": 15, "oc": 2}], "gx9eqfjpbg": [{"id": 371991, "mc": 140, "oc": 50}], "gxj5zcf2bx": [{"id": 372155, "mc": 17, "oc": 4}], "gxg2fyd3u6": [{"id": 372686, "mc": 8, "oc": 3}], "gx5gt3dgab": [{"id": 373245, "mc": 39, "oc": 9}], "gxcvrgtvue": [{"id": 374035, "mc": 123, "oc": 3}], "gxeyujrzpt": [{"id": 374885, "mc": 2843, "oc": 532}], "gxgdquw": [{"id": 375711, "mc": 97, "oc": 27}], "gxkwymead8": [{"id": 375830, "mc": 39, "oc": 8}], "gxxzuspty3": [{"id": 377090, "mc": 170, "oc": 12}], "gxtwvkqn7q": [{"id": 377468, "mc": 83, "oc": 34}], "gx22ypcve8": [{"id": 377735, "mc": 2788, "oc": 209}], "gx9nyueqyc": [{"id": 377924, "mc": 53, "oc": 10}], "gx2yfwp2nq": [{"id": 378197, "mc": 175, "oc": 8}], "gxhxh2uqtc": [{"id": 378952, "mc": 64, "oc": 6}], "gxws4j4efh": [{"id": 379242, "mc": 111, "oc": 16}], "gx4qfjp4kt": [{"id": 380489, "mc": 103, "oc": 1}], "gxedqznxqk": [{"id": 380789, "mc": 4, "oc": 3}], "gxub8zh": [{"id": 380947, "mc": 40, "oc": 1}], "gxeyymaqtp": [{"id": 381366, "mc": 47, "oc": 18}], "gxkrbswygb": [{"id": 382629, "mc": 11, "oc": 4}], "gxhmnbcwuf": [{"id": 382846, "mc": 1623, "oc": 201}], "gxeftgketq": [{"id": 383340, "mc": 22, "oc": 3}], "gxa37hexr7": [{"id": 383403, "mc": 944, "oc": 127}], "gxpkp3ukxt": [{"id": 383652, "mc": 331, "oc": 4}], "gxrhhxw": [{"id": 383697, "mc": 15, "oc": 3}], "gxtuh6r": [{"id": 384073, "mc": 17, "oc": 4}], "gx8zvbr": [{"id": 384478, "mc": 6, "oc": 1}], "gxmmjcrnzr": [{"id": 384558, "mc": 49, "oc": 12}], "gxpdzf6v7r": [{"id": 385217, "mc": 176, "oc": 7}], "gxkczk4ts": [{"id": 385767, "mc": 7012, "oc": 111}], "gxrqyrnsgc": [{"id": 387993, "mc": 1041, "oc": 18}], "gx8ekdw2ty": [{"id": 389458, "mc": 92, "oc": 7}], "gxvvp7g": [{"id": 389549, "mc": 3, "oc": 0}], "gxqkshm4gp": [{"id": 390501, "mc": 95, "oc": 8}], "gxtxyh5pvw": [{"id": 391312, "mc": 157, "oc": 34}], "gx3r2bdnwr": [{"id": 391758, "mc": 41, "oc": 5}], "gxkfks5": [{"id": 391854, "mc": 13, "oc": 2}], "gxftmvn": [{"id": 392425, "mc": 156, "oc": 3}], "gxvdsvrn5u": [{"id": 392467, "mc": 122, "oc": 18}], "gxbsqwxczn": [{"id": 392875, "mc": 21, "oc": 0}], "gxtsspj7zh": [{"id": 393282, "mc": 722, "oc": 59}], "gxg4a9a5dj": [{"id": 393898, "mc": 23, "oc": 6}], "gxzjg3ynaq": [{"id": 394009, "mc": 269, "oc": 26}], "gx55urapzh": [{"id": 394117, "mc": 280, "oc": 78}], "gxhekqrn36": [{"id": 394802, "mc": 25, "oc": 13}], "gxkdegksj8": [{"id": 396161, "mc": 391, "oc": 64}], "gxmzph8": [{"id": 396789, "mc": 397, "oc": 51}], "gxraexxxmt": [{"id": 397593, "mc": 44, "oc": 8}], "gxdfgahvny": [{"id": 397701, "mc": 12, "oc": 4}], "gxtgph2": [{"id": 398554, "mc": 9, "oc": 1}], "gxx3fk": [{"id": 398555, "mc": 176, "oc": 21}], "gxerwz7": [{"id": 399450, "mc": 43, "oc": 3}], "gx5udmm": [{"id": 399616, "mc": 46, "oc": 10}]}